vurze/__init__.py
vurze/_vurze.cpython-313-darwin.so
vurze/add_decorators.py
vurze/check_decorators.py
vurze/cli.py
vurze/dummy_decorators.py
vurze/remove_decorators.py
vurze/setup.py
vurze-0.1.2.dist-info/METADATA
vurze-0.1.2.dist-info/WHEEL
vurze-0.1.2.dist-info/entry_points.txt
vurze-0.1.2.dist-info/licenses/LICENSE
vurze-0.1.2.dist-info/RECORD
