Metadata-Version: 2.4
Name: vurze
Version: 0.1.2
Classifier: Development Status :: 3 - Alpha
Classifier: Intended Audience :: Developers
Classifier: License :: OSI Approved :: MIT License
Classifier: Programming Language :: Python :: 3
Classifier: Programming Language :: Python :: 3.8
Classifier: Programming Language :: Python :: 3.9
Classifier: Programming Language :: Python :: 3.10
Classifier: Programming Language :: Python :: 3.11
Classifier: Programming Language :: Python :: 3.12
Classifier: Programming Language :: Rust
Classifier: Programming Language :: Python :: Implementation :: CPython
Classifier: Programming Language :: Python :: Implementation :: PyPy
Classifier: Topic :: Security
Classifier: Topic :: Software Development :: Libraries :: Python Modules
Requires-Dist: python-dotenv>=1.0.0
Requires-Dist: typer>=0.9.0
Requires-Dist: pytest>=7.0.0 ; extra == 'test'
Requires-Dist: pytest-cov>=4.0.0 ; extra == 'test'
Requires-Dist: pytest-asyncio>=0.21.0 ; extra == 'test'
Provides-Extra: test
License-File: LICENSE
Summary: Version control your Python functions and classes with automated cryptographic decorator injection.
Keywords: rust,python,decorator,version-control,cryptography
Author: Aidan Dyga
License: MIT
Requires-Python: >=3.8
Project-URL: Issues, https://github.com/MCP-Security-Research/vurze/issues
Project-URL: Repository, https://github.com/MCP-Security-Research/vurze
